wrktoolboxxlsx/__init__.py
wrktoolboxxlsx/xlsx.py
wrktools_xlsx-0.0.5.dist-info/LICENSE
wrktools_xlsx-0.0.5.dist-info/METADATA
wrktools_xlsx-0.0.5.dist-info/WHEEL
wrktools_xlsx-0.0.5.dist-info/top_level.txt
wrktools_xlsx-0.0.5.dist-info/RECORD
