Metadata-Version: 2.1
Name: wrktools-xlsx
Version: 0.0.5
Summary: XLSX spreadsheet reports for wrktoolbox.
Home-page: https://github.com/RobertoPrevato/wrktoolbox-xlsx
Author: RobertoPrevato
Author-email: roberto.prevato@gmail.com
License: MIT
Keywords: wrk runner benchmarks load performance tests xlsx results
Platform: UNKNOWN
Classifier: Development Status :: 5 - Production/Stable
Classifier: License :: OSI Approved :: MIT License
Classifier: Programming Language :: Python :: 3
Classifier: Operating System :: Unix
Requires-Dist: wrktools
Requires-Dist: xlsxwriter
